pcpxlog/__init__.py
pcpxlog/configDemo.py
pcpxlog/cpxHandlers.py
pcpxlog/cpxLoader.py
pcpxlog/cpxLogger.py
pcpxlog/cpxUtils.py
pcpxlog-0.1.dist-info/LICENSE
pcpxlog-0.1.dist-info/METADATA
pcpxlog-0.1.dist-info/WHEEL
pcpxlog-0.1.dist-info/entry_points.txt
pcpxlog-0.1.dist-info/top_level.txt
pcpxlog-0.1.dist-info/RECORD
