Metadata-Version: 2.1
Name: pcpxlog
Version: 0.1
Summary: Simple configuration allows log output to console, file, database at the same time
Home-page: https://github.com/kerbalwzy/PCPXlog
Author: WangZhongYing
Author-email: kerbalwzy@gmail.com
License: Mozilla Public License Version 2.0
Keywords: cpxlog,pcpxlog,kerbalwzy,wangzhongying
Platform: UNKNOWN
Requires-Python: >=3
Requires-Dist: pymongo
